Metadata-Version: 1.1
Name: easypkg
Version: 0.1.1
Summary: Easy downloader of private repositories.
Home-page: https://github.com/jotajunior/easypkg
Author: Jota Junior
Author-email: jotavrj@gmail.com
License: UNKNOWN
Download-URL: https://github.com/jotajunior/easypkg/tarball/0.1.1
Keywords: bitbucket,github,private,repository,download,repo
Platform: UNKNOWN
